LICENSE.txt
README.rst
setup.cfg
setup.py
src/api_compose/README.rst
src/api_compose/__init__.py
src/api_compose/app.py
src/api_compose/version.py
src/api_compose.egg-info/PKG-INFO
src/api_compose.egg-info/SOURCES.txt
src/api_compose.egg-info/dependency_links.txt
src/api_compose.egg-info/entry_points.txt
src/api_compose.egg-info/requires.txt
src/api_compose.egg-info/top_level.txt
src/api_compose/cli/__init__.py
src/api_compose/cli/events.py
src/api_compose/cli/main.py
src/api_compose/cli/options.py
src/api_compose/cli/commands/__init__.py
src/api_compose/cli/commands/config.py
src/api_compose/cli/scaffold_data/README.rst
src/api_compose/cli/scaffold_data/config.yaml
src/api_compose/cli/scaffold_data/test_e2e.py
src/api_compose/cli/scaffold_data/envs/base-env.yaml
src/api_compose/cli/scaffold_data/functions/__init__.py
src/api_compose/cli/scaffold_data/manifests/actions/json_http_action.yaml
src/api_compose/cli/scaffold_data/manifests/actions/xml_http_action.yaml
src/api_compose/cli/scaffold_data/manifests/specifications/some_specifications.yaml
src/api_compose/cli/session_builder/__init__.py
src/api_compose/cli/session_builder/filters.py
src/api_compose/cli/session_builder/selectors.py
src/api_compose/cli/session_builder/validators.py
src/api_compose/cli/utils/__init__.py
src/api_compose/cli/utils/parser.py
src/api_compose/cli/utils/yaml_dumper.py
src/api_compose/core/__init__.py
src/api_compose/core/annotations.py
src/api_compose/core/events/__init__.py
src/api_compose/core/events/base.py
src/api_compose/core/events/default.py
src/api_compose/core/events/jinja.py
src/api_compose/core/events/read_config.py
src/api_compose/core/events/scheduler.py
src/api_compose/core/jinja/__init__.py
src/api_compose/core/jinja/exceptions.py
src/api_compose/core/jinja/core/__init__.py
src/api_compose/core/jinja/core/context.py
src/api_compose/core/jinja/core/engine.py
src/api_compose/core/jinja/core/loader.py
src/api_compose/core/jinja/core/utils.py
src/api_compose/core/logging/__init__.py
src/api_compose/core/logging/adapter.py
src/api_compose/core/lxml/__init__.py
src/api_compose/core/lxml/parser.py
src/api_compose/core/serde/__init__.py
src/api_compose/core/serde/base.py
src/api_compose/core/serde/integer.py
