Metadata-Version: 2.1
Name: api-compose
Version: 0.0.20
Summary: A Framework for orchestrating, asserting and reporting on API calls with templates
Author: Ken
Author-email: kenho811job@gmail.com
License: Apache License 2.0
Classifier: Programming Language :: Python :: 3
Requires-Python: >=3.9
Provides-Extra: test
Provides-Extra: dist
Provides-Extra: tutorials
License-File: LICENSE.txt
